useful_scripts/__init__.py
useful_scripts/downloader/__init__.py
useful_scripts/downloader/multi_thread_downloader.py
useful_scripts/main.py
useful_scripts/markdown/__init__.py
useful_scripts/markdown/main.py
useful_scripts/markdown/obsidian_config_zipper.py
useful_scripts/markdown/readme_handler.py
useful_scripts/painter/__init__.py
useful_scripts/paths/__init__.py
useful_scripts/paths/main.py
useful_scripts/paths/paths.py
useful_scripts/paths/translater.py
useful_scripts/rich_logger.py
useful_scripts/unzipper.py
useful_scripts-0.4.532.dist-info/entry_points.txt
useful_scripts-0.4.532.dist-info/METADATA
useful_scripts-0.4.532.dist-info/WHEEL
useful_scripts-0.4.532.dist-info/RECORD
